{"results" :
    [
        {
        "image" : "https://juhan3.github.io/exhibition/pride/images/08.jpng",
        "title" : "2023 제24회 서울퀴어퍼레이드(SQP) 자원활동가를 모집",
        "person": "",
        "contents" : "서울퀴어퍼레이드(Seoul Queer Parade, SQP)는 성소수자 가시화, 인권증진, 문화향유, 자긍심 고취를 위해 매년 개최되는 도심 야외를 주 무대로 하는 공개‧문화행사입니다. 전 세계적으로 수많은 도시에서 열리는 프라이드 퍼레이드(Pride Parade, 자긍심 행진)와 궤를 같이 합니다.\n\n부스, 무대, 퍼레이드(행진) 등의 프로그램으로 구성되어 있습니다.\n\n자발적으로 참여한 시민들로 구성된 서울퀴어문화축제조직위원회가 주최하고, 내부기구인 서울퀴어퍼레이드집행위원회가 주관합니다.\n\n2023 제24회 서울퀴어퍼레이드에서 활동내용에 따라 나뉜 각 팀*에 소속되어 행사 운영에 적극적으로 함께할  자원활동가분들을 모집합니다. 서울 도심에 함께 무지개를 펼쳐낼 분들을 기대합니다.\n\nThe Seoul Queer Parade (SQP) is an open and cultural event held annually in the heart of the city, with the aim of raising visibility for sexual minorities, promoting human rights, enjoying culture, and fostering self-esteem. It is part of the Pride Parade movement that takes place in numerous cities worldwide.The event consists of various programs, including booths, stages, and the parade itself.The Seoul Queer Culture Festival Organizing Committee, composed of voluntary citizen participants, organizes the Seoul Queer Parade, while the Seoul Queer Parade Executive Committee, an internal body, takes charge of the event management.For the 24th Seoul Queer Parade in 2023, recruitment is open for individuals who wish to actively participate in the event's operation as volunteers, divided into different teams based on their respective activities. We look forward to welcoming those who will join us in spreading rainbows across the streets of Seoul.\n\n",
        "location" : "서울퀴어퍼레이드(SQP)", 
        "whendate" : "",
        "url" : "https://www.sqcf.org/notice/?bmode=view&idx=15281248",
        "youtubeurl" : ""
        }
    ]
}
